logsetup/__init__.py
logsetup/compat.py
logsetup/handlers.py
logsetup/logger.py
logsetup/mailgun_api.py
logsetup-1.5.dist-info/licenses/license
logsetup-1.5.dist-info/METADATA
logsetup-1.5.dist-info/WHEEL
logsetup-1.5.dist-info/top_level.txt
logsetup-1.5.dist-info/RECORD
