Metadata-Version: 2.4
Name: logsetup
Version: 1.5
Summary: Python log initialization made easy
Author-email: Carter Temm <cartertemm@gmail.com>
License-Expression: MIT
Project-URL: Homepage, https://github.com/cartertemm/logsetup
Classifier: Programming Language :: Python :: 3
Classifier: Operating System :: OS Independent
Classifier: Development Status :: 4 - Beta
Classifier: Topic :: System :: Logging
Requires-Python: >=3.8
License-File: license
Requires-Dist: pyprowl
Requires-Dist: requests
Dynamic: license-file
